odoo/addons/base_multi_company/README.rst
odoo/addons/base_multi_company/__init__.py
odoo/addons/base_multi_company/__manifest__.py
odoo/addons/base_multi_company/hooks.py
odoo/addons/base_multi_company/i18n/base_multi_company.pot
odoo/addons/base_multi_company/i18n/es.po
odoo/addons/base_multi_company/i18n/es_AR.po
odoo/addons/base_multi_company/i18n/fr.po
odoo/addons/base_multi_company/i18n/hr.po
odoo/addons/base_multi_company/i18n/nl_NL.po
odoo/addons/base_multi_company/i18n/pt.po
odoo/addons/base_multi_company/i18n/pt_BR.po
odoo/addons/base_multi_company/i18n/zh_CN.po
odoo/addons/base_multi_company/models/__init__.py
odoo/addons/base_multi_company/models/multi_company_abstract.py
odoo/addons/base_multi_company/readme/CONTRIBUTORS.rst
odoo/addons/base_multi_company/readme/DESCRIPTION.rst
odoo/addons/base_multi_company/readme/USAGE.rst
odoo/addons/base_multi_company/static/description/icon.png
odoo/addons/base_multi_company/static/description/index.html
odoo/addons/base_multi_company/tests/__init__.py
odoo/addons/base_multi_company/tests/common.py
odoo/addons/base_multi_company/tests/multi_company_abstract_tester.py
odoo/addons/base_multi_company/tests/test_multi_company_abstract.py
odoo13_addon_base_multi_company-13.0.1.0.3.dist-info/METADATA
odoo13_addon_base_multi_company-13.0.1.0.3.dist-info/WHEEL
odoo13_addon_base_multi_company-13.0.1.0.3.dist-info/top_level.txt
odoo13_addon_base_multi_company-13.0.1.0.3.dist-info/RECORD
