Metadata-Version: 2.1
Name: odoo13-addon-base-multi-company
Version: 13.0.1.0.3
Summary: Provides a base for adding multi-company support to models.
Home-page: https://github.com/OCA/multi-company
Author: LasLabs, Tecnativa, Odoo Community Association (OCA)
Author-email: support@odoo-community.org
License: LGPL-3
Platform: UNKNOWN
Classifier: Programming Language :: Python
Classifier: Framework :: Odoo
Classifier: License :: OSI Approved :: GNU Lesser General Public License v3 (LGPLv3)
Classifier: Development Status :: 5 - Production/Stable
Requires-Python: >=3.5
Requires-Dist: odoo (<13.1dev,>=13.0a)
